divbase_cli/__init__.py
divbase_cli/cli_config.py
divbase_cli/cli_exceptions.py
divbase_cli/config_resolver.py
divbase_cli/display_task_history.py
divbase_cli/divbase_cli.py
divbase_cli/pre_signed_urls.py
divbase_cli/services.py
divbase_cli/user_auth.py
divbase_cli/user_config.py
divbase_cli/cli_commands/__init__.py
divbase_cli/cli_commands/auth_cli.py
divbase_cli/cli_commands/dimensions_cli.py
divbase_cli/cli_commands/file_cli.py
divbase_cli/cli_commands/query_cli.py
divbase_cli/cli_commands/task_history_cli.py
divbase_cli/cli_commands/user_config_cli.py
divbase_cli/cli_commands/version_cli.py
divbase_cli-0.1.0.dev2.dist-info/METADATA
divbase_cli-0.1.0.dev2.dist-info/WHEEL
divbase_cli-0.1.0.dev2.dist-info/entry_points.txt
divbase_cli-0.1.0.dev2.dist-info/RECORD
