Metadata-Version: 2.4
Name: divbase-cli
Version: 0.1.0.dev2
Summary: Command Line Interface for Divbase
Project-URL: Homepage, https://divbase.scilifelab.se
Project-URL: Documentation, https://scilifelabdatacentre.github.io/divbase
Project-URL: Repository, https://github.com/ScilifelabDataCentre/divbase
Project-URL: Issues, https://github.com/ScilifelabDataCentre/divbase/issues
Author-email: SciLifeLab Data Centre <datacentre@scilifelab.se>
License-Expression: MIT
Classifier: Development Status :: 3 - Alpha
Classifier: Environment :: Console
Classifier: Intended Audience :: Science/Research
Classifier: License :: OSI Approved :: MIT License
Classifier: Operating System :: OS Independent
Classifier: Programming Language :: Python :: 3
Classifier: Programming Language :: Python :: 3.12
Classifier: Programming Language :: Python :: 3.13
Classifier: Programming Language :: Python :: 3.14
Requires-Python: >=3.12
Requires-Dist: divbase-lib==0.1.0.dev2
Requires-Dist: httpx<2,>=0.28.1
Requires-Dist: typer<1,>=0.21.1
